byted_overpass_content_review_content_process_go/__init__.py
byted_overpass_content_review_content_process_go-0.0.1.dist-info/METADATA
byted_overpass_content_review_content_process_go-0.0.1.dist-info/WHEEL
byted_overpass_content_review_content_process_go-0.0.1.dist-info/top_level.txt
byted_overpass_content_review_content_process_go-0.0.1.dist-info/RECORD
